feature_service_client/__init__.py
feature_service_client/api/__init__.py
feature_service_client/api/default_api.py
feature_service_client/api_client.py
feature_service_client/apis/__init__.py
feature_service_client/configuration.py
feature_service_client/exceptions.py
feature_service_client/model/__init__.py
feature_service_client/model/columnar_features_response.py
feature_service_client/model/feature_column.py
feature_service_client/model/feature_request_data.py
feature_service_client/model/feature_value.py
feature_service_client/model/features_request.py
feature_service_client/model/seldon_features_request.py
feature_service_client/model_utils.py
feature_service_client/models/__init__.py
feature_service_client/rest.py
feature_service_client-0.1.1.dist-info/METADATA
feature_service_client-0.1.1.dist-info/WHEEL
feature_service_client-0.1.1.dist-info/RECORD
