Metadata-Version: 2.1
Name: feature-service-client
Version: 0.1.1
Summary: python client for talking to feature service
Author: Long Yao
Author-email: l2yao@tripadvisor.com
Requires-Python: >=3.6,<4.0
Classifier: Programming Language :: Python :: 3
Classifier: Programming Language :: Python :: 3.6
Classifier: Programming Language :: Python :: 3.7
Classifier: Programming Language :: Python :: 3.8
Classifier: Programming Language :: Python :: 3.9
Classifier: Programming Language :: Python :: 3.10
Classifier: Programming Language :: Python :: 3.11
